buffered_encryption/__init__.py
buffered_encryption/aesctr.py
buffered_encryption/aesgcm.py
buffered_encryption/crypt.py
buffered_encryption/utils.py
buffered_encryption-0.2.1.dist-info/LICENSE
buffered_encryption-0.2.1.dist-info/METADATA
buffered_encryption-0.2.1.dist-info/WHEEL
buffered_encryption-0.2.1.dist-info/top_level.txt
buffered_encryption-0.2.1.dist-info/RECORD
