Metadata-Version: 2.1
Name: buffered-encryption
Version: 0.2.1
Summary: Encrypt large files without loading the entire file into memory.
Home-page: https://github.com/eblocha/buffered-encryption
Author: Elliott Blocha
License: MIT
Keywords: cryptography,big,large,encryption
Platform: UNKNOWN
Classifier: Development Status :: 3 - Alpha
Classifier: Topic :: Utilities
Classifier: License :: OSI Approved :: MIT License
Classifier: Programming Language :: Python :: 3
Classifier: Programming Language :: Python :: 3.6
Classifier: Programming Language :: Python :: 3.7
Classifier: Programming Language :: Python :: 3.8
Classifier: Programming Language :: Python :: 3.9
Classifier: Programming Language :: Python :: 3 :: Only
Requires-Python: >=3.6, <4
Requires-Dist: cryptography
